CMakeLists.txt
LICENSE.txt
MANIFEST.in
README.md
pyproject.toml
setup.cfg
setup.py
src/CMakeLists.txt
src/cbessel.f90
src/ddx.f90
src/ddx.h
src/ddx_cinterface.f90
src/ddx_constants.f90
src/ddx_core.f90
src/ddx_cosmo.f90
src/ddx_definitions.f90
src/ddx_driver.f90
src/ddx_errors.f90
src/ddx_gradients.f90
src/ddx_harmonics.f90
src/ddx_legacy.f90
src/ddx_lpb.f90
src/ddx_lpb_core.f90
src/ddx_multipolar_solutes.f90
src/ddx_operators.f90
src/ddx_parameters.f90
src/ddx_pcm.f90
src/ddx_solvers.f90
src/ddx_workspace.f90
src/llgnew.f
src/pyddx.cpp
src/pyddx_classes.cpp
src/pyddx_data.cpp
src/test_gradients.py
src/test_lpb_limits.py
src/test_multipoles.py
src/test_pyddx.py
src/pyddx.egg-info/PKG-INFO
src/pyddx.egg-info/SOURCES.txt
src/pyddx.egg-info/dependency_links.txt
src/pyddx.egg-info/not-zip-safe
src/pyddx.egg-info/requires.txt
src/pyddx.egg-info/top_level.txt