Metadata-Version: 2.1
Name: pyddx
Version: 0.6.7
Summary: ddX continuum solvation library
Author-email: ddX developers <best@ians.uni-stuttgart.de>
License:                    GNU LESSER GENERAL PUBLIC LICENSE
Project-URL: Homepage, https://ddsolvation.github.io/ddX
Project-URL: Source, https://github.com/ddsolvation/ddX
Project-URL: Issues, https://github.com/ddsolvation/ddX/issues
Platform: Linux
Platform: Mac OS-X
Requires-Python: >=3.8
Provides-Extra: test
License-File: LICENSE.txt
